yolov5facedetector/__init__.py
yolov5facedetector/face_detector.py
yolov5facedetector/models/__init__.py
yolov5facedetector/models/common.py
yolov5facedetector/models/experimental.py
yolov5facedetector/models/export.py
yolov5facedetector/models/yolo.py
yolov5facedetector/models/yolov5-0.5.yaml
yolov5facedetector/models/yolov5l.yaml
yolov5facedetector/models/yolov5l6.yaml
yolov5facedetector/models/yolov5m.yaml
yolov5facedetector/models/yolov5m6.yaml
yolov5facedetector/models/yolov5n.yaml
yolov5facedetector/models/yolov5n6.yaml
yolov5facedetector/models/yolov5s.yaml
yolov5facedetector/models/yolov5s6.yaml
yolov5facedetector/utils/__init__.py
yolov5facedetector/utils/activations.py
yolov5facedetector/utils/autoanchor.py
yolov5facedetector/utils/datasets.py
yolov5facedetector/utils/face_datasets.py
yolov5facedetector/utils/general.py
yolov5facedetector/utils/google_utils.py
yolov5facedetector/utils/infer_utils.py
yolov5facedetector/utils/loss.py
yolov5facedetector/utils/metrics.py
yolov5facedetector/utils/plots.py
yolov5facedetector/utils/torch_utils.py
yolov5facedetector/utils/aws/__init__.py
yolov5facedetector/utils/aws/resume.py
yolov5facedetector/utils/wandb_logging/__init__.py
yolov5facedetector/utils/wandb_logging/log_dataset.py
yolov5facedetector/utils/wandb_logging/wandb_utils.py
yolov5facedetector/weights/__init__.py
yolov5facedetector/weights/yoloface_type.py
yolov5facedetector-1.0.2.dist-info/LICENSE
yolov5facedetector-1.0.2.dist-info/METADATA
yolov5facedetector-1.0.2.dist-info/WHEEL
yolov5facedetector-1.0.2.dist-info/top_level.txt
yolov5facedetector-1.0.2.dist-info/RECORD
