Metadata-Version: 2.1
Name: yolov5facedetector
Version: 1.0.2
Summary: Packaged version YOLOv5 Face Detector
Home-page: UNKNOWN
Author: BenedictusAryo
Author-email: benedictusaryo@outlook.com
License: UNKNOWN
Platform: UNKNOWN
Classifier: Programming Language :: Python :: 3
Classifier: License :: OSI Approved :: GNU General Public License v3 (GPLv3)
Classifier: Operating System :: OS Independent
Requires-Python: >=3.6.0
Requires-Dist: thop (>=0.0.31.post2005241907)
Requires-Dist: scipy (>=1.7.2)
Requires-Dist: seaborn (>=0.11.1)
Requires-Dist: joblib (>=1.0.1)
Requires-Dist: matplotlib (>=3.4.3)
Requires-Dist: torch (>=1.10.1+cu113)
Requires-Dist: pandas (>=1.3.4)
Requires-Dist: opencv-python (>=4.5.3.56)
Requires-Dist: tqdm (>=4.62.3)
Requires-Dist: numpy (>=1.20.3)
Requires-Dist: torchvision (>=0.11.2+cu113)
Requires-Dist: requests (>=2.25.1)
Requires-Dist: onnx (>=1.10.2)
Requires-Dist: Pillow (>=9.0.0)
Requires-Dist: PyYAML (>=6.0)
Requires-Dist: wandb (>=0.12.9)
